signxai2/__init__.py
signxai2/composites.py
signxai2/dftutils.py
signxai2/misc.py
signxai2/rules.py
signxai2/sign.py
signxai2-0.15.10.dist-info/METADATA
signxai2-0.15.10.dist-info/WHEEL
signxai2-0.15.10.dist-info/licenses/COPYING.LESSER
signxai2-0.15.10.dist-info/licenses/COPYING.txt
signxai2-0.15.10.dist-info/licenses/LICENSE_DFT-LRP
signxai2-0.15.10.dist-info/RECORD
