Metadata-Version: 2.4
Name: signxai2
Version: 0.15.10
Summary: Extended variant of ZeNNit with SIGNed explanations - Unveiling relevant features by reducing bias
Project-URL: Documentation, https://TimeXAIgroup.github.io/signxai2/index.html
Project-URL: Repository, https://github.com/TimeXAIgroup/signxai2.git
Project-URL: Bug Reports, https://github.com/TimeXAIgroup/signxai2/issues
Project-URL: Publication, https://www.sciencedirect.com/science/article/pii/S1566253523001999?via%3Dihub
Author-email: TimeXAIgroup <jennifer.hannig@kite.thm.de>, Nils Gumpfer <nils.gumpfer@kite.thm.de>
Maintainer-email: Nils Gumpfer <nils.gumpfer@kite.thm.de>
License-Expression: GPL-3.0
License-File: COPYING.LESSER
License-File: COPYING.txt
License-File: LICENSE_DFT-LRP
Keywords: Artificial Intelligence,Deep Learning,Explainable AI,Feature Attribution,Interpretability,Machine Learning,SIGN,XAI
Classifier: Development Status :: 3 - Alpha
Classifier: Intended Audience :: Science/Research
Classifier: License :: OSI Approved :: GNU General Public License v3 or later (GPLv3+)
Classifier: License :: OSI Approved :: GNU Lesser General Public License v3 or later (LGPLv3+)
Classifier: Natural Language :: English
Classifier: Programming Language :: Python :: 3.11
Classifier: Programming Language :: Python :: 3.12
Classifier: Programming Language :: Python :: 3.13
Classifier: Topic :: Scientific/Engineering :: Artificial Intelligence
Requires-Python: >=3.11.11
Requires-Dist: lxt==2.1
Requires-Dist: zennit==1.0.0
